nvn/__init__.py
nvn/__main__.py
nvn/cli.py
nvn-4.1.6.dist-info/entry_points.txt
nvn-4.1.6.dist-info/LICENSE
nvn-4.1.6.dist-info/WHEEL
nvn-4.1.6.dist-info/METADATA
nvn-4.1.6.dist-info/RECORD
