Metadata-Version: 2.1
Name: nvn
Version: 4.1.6
Summary: nvn
License: MIT
Author: Ardustri
Author-email: social.linter@gmail.com
Requires-Python: >=3.7,<4.0
Classifier: License :: OSI Approved :: MIT License
Classifier: Programming Language :: Python :: 3
Classifier: Programming Language :: Python :: 3.7
Classifier: Programming Language :: Python :: 3.8
Classifier: Programming Language :: Python :: 3.9
Requires-Dist: ardlib
Requires-Dist: click
Requires-Dist: pyyaml
Requires-Dist: watchgod
